__init__.py
msftoolbox/_version.py
msftoolbox/acled/README.md
msftoolbox/acled/__init__.py
msftoolbox/acled/data.py
msftoolbox/azure/README.md
msftoolbox/azure/__init__.py
msftoolbox/azure/azure_keyvault.py
msftoolbox/azure/azure_open_ai.py
msftoolbox/azure/azure_sql.py
msftoolbox/azure/azure_storage_container.py
msftoolbox/dhis2/README.md
msftoolbox/dhis2/__init__.py
msftoolbox/dhis2/data.py
msftoolbox/dhis2/metadata.py
msftoolbox/gdelt/README.md
msftoolbox/gdelt/__init__.py
msftoolbox/gdelt/data.py
msftoolbox/kobo/README.md
msftoolbox/kobo/__init__.py
msftoolbox/kobo/data.py
msftoolbox/modis/README.md
msftoolbox/modis/__init__.py
msftoolbox/modis/data.py
msftoolbox/powerbi/README.md
msftoolbox/powerbi/__init__.py
msftoolbox/powerbi/report.py
msftoolbox/powerbi/workspace.py
msftoolbox/reliefweb/README.md
msftoolbox/reliefweb/__init__.py
msftoolbox/reliefweb/data.py
msftoolbox/sharepoint/README.md
msftoolbox/sharepoint/files.py
msftoolbox/topdesk/README.md
msftoolbox/topdesk/data.py
msftoolbox/unidata/README.md
msftoolbox/unidata/__init__.py
msftoolbox/unidata/data.py
msftoolbox-0.2.3.dist-info/licenses/LICENSE
tests/conftest.py
tests/test_dhis2.py
tests/test_gdelt.py
tests/test_kobo.py
tests/test_methods.py
tests/test_modis.py
tests/test_reliefweb.py
tests/test_unidata.py
msftoolbox-0.2.3.dist-info/METADATA
msftoolbox-0.2.3.dist-info/WHEEL
msftoolbox-0.2.3.dist-info/top_level.txt
msftoolbox-0.2.3.dist-info/RECORD
