Metadata-Version: 2.4
Name: msftoolbox
Version: 0.2.3
Summary: A python toolbox containing wrappers facilitating common operations.
Classifier: Programming Language :: Python :: 3
Classifier: License :: OSI Approved :: MIT License
Classifier: Operating System :: OS Independent
Requires-Python: >=3.10
License-File: LICENSE
Requires-Dist: numpy
Requires-Dist: pandas
Requires-Dist: requests
Requires-Dist: azure-identity>=1.16.1
Requires-Dist: azure-keyvault==4.2.0
Requires-Dist: azure-keyvault-certificates==4.6.0
Requires-Dist: azure-keyvault-keys==4.7.0
Requires-Dist: azure-keyvault-secrets==4.6.0
Requires-Dist: azure-storage-blob==12.14.1
Requires-Dist: azure-mgmt-core==1.3.2
Requires-Dist: azure-mgmt-resource==21.1.0
Requires-Dist: openai==1.55.3
Requires-Dist: Office365-REST-Python-Client==2.5.13
Requires-Dist: newspaper3k==0.2.8
Requires-Dist: lxml_html_clean==0.1.1
Requires-Dist: SQLAlchemy==2.0.36
Requires-Dist: pyodbc==5.2.0
Provides-Extra: dev
Requires-Dist: pytest; extra == "dev"
Requires-Dist: pylint; extra == "dev"
Dynamic: license-file
